chatly/__init__.py
chatly/__main__.py
chatly/application.py
chatly/core/__init__.py
chatly/core/config.py
chatly/core/constants.py
chatly/core/converters.py
chatly/core/document_manager.py
chatly/core/threads.py
chatly/core/translate.py
chatly/pages/__init__.py
chatly/pages/browser_page.py
chatly/pages/chat_page.py
chatly/pages/documents_page.py
chatly/pages/explorer_page.py
chatly/pages/log_page.py
chatly/pages/ocr_page.py
chatly/pages/settings_page.py
chatly/pages/start_page.py
chatly/py.typed
chatly/widgets/__init__.py
chatly/widgets/preview_widget.py
chatly/widgets/vector_dbs/__init__.py
chatly/widgets/vector_dbs/container.py
chatly/widgets/vector_dbs/tree.py
chatly/windows/__init__.py
chatly/windows/main_window.py
chatly-1.0.0.dist-info/WHEEL
chatly-1.0.0.dist-info/entry_points.txt
chatly-1.0.0.dist-info/METADATA
chatly-1.0.0.dist-info/RECORD
