Metadata-Version: 2.3
Name: chatly
Version: 1.0.0
Summary: Agent desktop app
Keywords: 
Author: Philipp Temminghoff
Author-email: Philipp Temminghoff <philipptemminghoff@googlemail.com>
License: MIT License
Classifier: Development Status :: 4 - Beta
Classifier: Framework :: Pydantic
Classifier: Framework :: Pydantic :: 2
Classifier: Intended Audience :: Developers
Classifier: Operating System :: OS Independent
Classifier: Programming Language :: Python :: 3
Classifier: Programming Language :: Python :: 3 :: Only
Classifier: Programming Language :: Python :: 3.12
Classifier: Programming Language :: Python :: 3.13
Classifier: Programming Language :: Python :: 3.14
Classifier: Topic :: Documentation
Classifier: Topic :: Software Development
Classifier: Topic :: Utilities
Classifier: Typing :: Typed
Requires-Dist: comrak>=0.0.6
Requires-Dist: docler[all]>=0.2.0
Requires-Dist: mkconvert[comrak]>=0.11.5
Requires-Dist: mkdown>=0.1.1
Requires-Dist: prettyqt[pyside6]
Requires-Dist: pydantic
Requires-Python: >=3.13
Project-URL: Code coverage, https://app.codecov.io/gh/phil65/chatly
Project-URL: Discussions, https://github.com/phil65/chatly/discussions
Project-URL: Documentation, https://phil65.github.io/chatly/
Project-URL: Issues, https://github.com/phil65/chatly/issues
Project-URL: Source, https://github.com/phil65/chatly
